cattr/__init__.py
cattr/_compat.py
cattr/converters.py
cattr/disambiguators.py
cattr/function_dispatch.py
cattr/generation.py
cattr/multistrategy_dispatch.py
cattr/py.typed
cattrs_3.8-0.9.1.dist-info/LICENSE
cattrs_3.8-0.9.1.dist-info/METADATA
cattrs_3.8-0.9.1.dist-info/WHEEL
cattrs_3.8-0.9.1.dist-info/top_level.txt
cattrs_3.8-0.9.1.dist-info/RECORD
